{
  "ids": {
    "Todo": 5,
    "Student": 7,
    "SchoolStudent": 2
  },
  "models": {
    "Todo": {
      "1": "{\"title\":\"Take over the galaxy\",\"desc\":\"MWAHAHAHAHAHAHAHAHAHAHAHAHAMWAHAHAHAHAHAHAHAHAHAHAHAHA\",\"id\":1}",
      "2": "{\"title\":\"destroy alderaan\",\"desc\":\"Make sure there are no survivors left!\",\"id\":2}",
      "3": "{\"title\":\"play space invaders\",\"desc\":\"Become the very best!\",\"id\":3}",
      "4": "{\"title\":\"crush rebel scum\",\"desc\":\"Every.Last.One.\",\"id\":4}"
    },
    "Student": {
      "1": "{\"name\":\"jun\",\"studentCode\":\"2015112391\",\"wechatToken\":\"kro342rj432jtr3r3r\",\"studentId\":1}",
      "2": "{\"name\":\"keyne\",\"studentCode\":\"2015112331\",\"wechatToken\":\"kro342rj432jtr3r3r\",\"studentId\":2}",
      "3": "{\"name\":\"jane\",\"studentCode\":\"201511291\",\"wechatToken\":\"kro342rj432jtr3r3r\",\"studentId\":3}",
      "4": "{\"name\":\"jun\",\"studentCode\":\"201511292\",\"wechatToken\":\"ab.123.cd\",\"studentId\":4}",
      "5": "{\"name\":\"joe\",\"password\":\"1234\",\"major\":\"computer science\",\"studentCode\":\"123456\",\"studentId\":5,\"wechatToken\":\"imnewtokennewWechatToken\"}",
      "6": "{\"name\":\"tang\",\"password\":\"1234\",\"major\":\"computer science\",\"studentCode\":\"1996\",\"wechatToken\":\"9.a.9\",\"studentId\":6}"
    },
    "SchoolStudent": {
      "1": "{\"studentCode\":\"1234\",\"password\":\"1234\",\"schoolStudentId\":1}"
    }
  }
}